inklevel-0.1.2.dist-info/RECORD
inklevel-0.1.2.dist-info/WHEEL
inklevel-0.1.2.dist-info/metadata.json
inklevel-0.1.2.dist-info/DESCRIPTION.rst
inklevel-0.1.2.dist-info/METADATA
inklevel-0.1.2.dist-info/top_level.txt
inklevel/_constants.py
inklevel/_cbindings.py
inklevel/__init__.py
inklevel/_version.py
