Metadata-Version: 2.0
Name: inklevel
Version: 0.1.2
Summary: Python wrapper for libinklevel
Home-page: https://github.com/tom-mi/python-inklevel/
Author: Thomas Reifenberger
Author-email: tom-mi at rfnbrgr.de
License: GPLv2
Platform: any
Classifier: License :: OSI Approved :: GNU General Public License v2 (GPLv2)
Classifier: Programming Language :: Python
Classifier: Programming Language :: Python :: 2
Classifier: Programming Language :: Python :: 2.7
Classifier: Programming Language :: Python :: 3
Classifier: Programming Language :: Python :: 3.2
Classifier: Programming Language :: Python :: 3.3
Classifier: Programming Language :: Python :: 3.4
Classifier: Development Status :: 4 - Beta
Classifier: Intended Audience :: Developers
Classifier: Topic :: System :: Monitoring
Requires-Dist: enum34
